Metadata-Version: 2.1
Name: ofxstatement-nl-ing
Version: 0.1.0
Summary: OFXStatement plugin for ING (Netherlands)
Home-page: https://github.com/rhbvkleef/ofxstatement-nl-ing
Author: Rolf van Kleef
Author-email: pypi-ofxstatement-nl-ing@rolfvankleef.nl
License: GPLv3
Keywords: ofx,banking,statement
Platform: UNKNOWN
Classifier: Development Status :: 4 - Beta
Classifier: Programming Language :: Python :: 3
Classifier: Natural Language :: English
Classifier: Topic :: Office/Business :: Financial :: Accounting
Classifier: Topic :: Utilities
Classifier: Environment :: Console
Classifier: Operating System :: OS Independent
Classifier: License :: OSI Approved :: GNU Affero General Public License v3
Provides-Extra: test
